{
  "base": {
    "botToken": "",
    "homeChannel": "",
    "homeServerId": "",
    "wolframAlphaAppId": "",

    "authorizedUsers": [
      "",
      ""
    ],

    "sshHosts": [
      "",
      ""
    ]
  },

  "workerLinks": {
    "baseUrl": "",
    "secret": "",
    "namespaceId": "",
    "apiKey": "",
    "accountId": "",
    "email": ""
  },

  "s3": {
    "bucket": "",
    "cdnBaseUrl": "",
    "endpoint": "",
    "accessKey": "",
    "secretKey": "",
    "region": ""
  },

  "cloudflare": {
    "urlPrefix": "",
    "zoneId": "",
    "token": ""
  },

  "logs": {
    "slashCommands": {
      "logChannel": "",
      "cmdLogExcludedGuilds": [
        "",
        ""
      ]
    }
  }
}